aspyx/__init__.py
aspyx/di/__init__.py
aspyx/di/di.py
aspyx/di/aop/__init__.py
aspyx/di/aop/aop.py
aspyx/di/configuration/__init__.py
aspyx/di/configuration/configuration.py
aspyx/di/configuration/env_configuration_source.py
aspyx/di/configuration/yaml_configuration_source.py
aspyx/di/threading/__init__.py
aspyx/di/threading/synchronized.py
aspyx/exception/__init__.py
aspyx/exception/exception_manager.py
aspyx/mapper/__init__.py
aspyx/mapper/convert.py
aspyx/mapper/mapper.py
aspyx/mapper/operation_builder.py
aspyx/mapper/transformer.py
aspyx/reflection/__init__.py
aspyx/reflection/proxy.py
aspyx/reflection/reflection.py
aspyx/threading/__init__.py
aspyx/threading/context_local.py
aspyx/threading/thread_local.py
aspyx/util/__init__.py
aspyx/util/copy_on_write_cache.py
aspyx/util/logger.py
aspyx/util/serialization.py
aspyx/util/stringbuilder.py
aspyx/validation/__init__.py
aspyx/validation/validation.py
aspyx-1.9.8.dist-info/METADATA
aspyx-1.9.8.dist-info/WHEEL
aspyx-1.9.8.dist-info/licenses/LICENSE
aspyx-1.9.8.dist-info/RECORD
