Metadata-Version: 2.4
Name: aspyx
Version: 1.9.8
Summary: A DI and AOP library for Python
Author-email: Andreas Ernst <andreas.ernst7@gmail.com>
License: MIT License
License-File: LICENSE
Requires-Python: >=3.9
Requires-Dist: cachetools~=5.5.2
Requires-Dist: pydantic<3.0,>=2.0
Requires-Dist: python-dotenv~=1.1.0
Requires-Dist: pyyaml~=6.0.2
